{
  "schemaVersion": "county-boundaries-v0.3.7",
  "stateCode": "NJ",
  "vintage": "2024",
  "source": {
    "agency": "U.S. Census Bureau",
    "product": "TIGER/Line county and county-equivalent boundaries",
    "vintage": "2024",
    "url": "https://www2.census.gov/geo/tiger/TIGER2024/COUNTY/tl_2024_us_county.zip",
    "retrieval": "server-side only",
    "geoidProperty": "GEOID",
    "simplification": "Douglas-Peucker ring simplification with deterministic 0.005 degree tolerance; rings are kept closed with minimum polygon vertices and empty outputs rejected"
  },
  "features": [
    {
      "type": "Feature",
      "properties": {
        "GEOID": "34037",
        "NAME": "Sussex",
        "NAMELSAD": "Sussex County",
        "STATEFP": "34",
        "COUNTYFP": "037"
      },
      "geometry": {
        "type": "Polygon",
        "coordinates": [
          [
            [
              -74.836041,
              41.279346
            ],
            [
              -74.792171,
              41.310841
            ],
            [
              -74.793216,
              41.322236
            ],
            [
              -74.766639,
              41.328157
            ],
            [
              -74.755097,
              41.345872
            ],
            [
              -74.725951,
              41.346192
            ],
            [
              -74.69558,
              41.357607
            ],
            [
              -74.36751,
              41.203241
            ],
            [
              -74.632378,
              40.973717
            ],
            [
              -74.64156,
              40.962199
            ],
            [
              -74.63644,
              40.942638
            ],
            [
              -74.653085,
              40.929644
            ],
            [
              -74.6528,
              40.921655
            ],
            [
              -74.711517,
              40.899168
            ],
            [
              -74.731928,
              40.920852
            ],
            [
              -74.769425,
              40.910934
            ],
            [
              -74.967464,
              41.095327
            ],
            [
              -74.991815,
              41.089132
            ],
            [
              -74.979985,
              41.110507
            ],
            [
              -74.923779,
              41.138011
            ],
            [
              -74.882638,
              41.18038
            ],
            [
              -74.859251,
              41.219432
            ],
            [
              -74.866925,
              41.231382
            ],
            [
              -74.846597,
              41.253594
            ],
            [
              -74.836041,
              41.279346
            ]
          ]
        ]
      }
    },
    {
      "type": "Feature",
      "properties": {
        "GEOID": "34007",
        "NAME": "Camden",
        "NAMELSAD": "Camden County",
        "STATEFP": "34",
        "COUNTYFP": "007"
      },
      "geometry": {
        "type": "Polygon",
        "coordinates": [
          [
            [
              -75.013331,
              39.954201
            ],
            [
              -75.015081,
              39.946813
            ],
            [
              -75.004261,
              39.941485
            ],
            [
              -74.975634,
              39.939708
            ],
            [
              -74.983901,
              39.926826
            ],
            [
              -74.962871,
              39.920223
            ],
            [
              -74.949614,
              39.898338
            ],
            [
              -74.930745,
              39.885908
            ],
            [
              -74.902963,
              39.791108
            ],
            [
              -74.894822,
              39.783312
            ],
            [
              -74.819419,
              39.788001
            ],
            [
              -74.736216,
              39.729775
            ],
            [
              -74.87726,
              39.608352
            ],
            [
              -74.902725,
              39.631879
            ],
            [
              -74.908883,
              39.665351
            ],
            [
              -74.930607,
              39.690869
            ],
            [
              -74.987551,
              39.706701
            ],
            [
              -75.024252,
              39.730582
            ],
            [
              -75.021309,
              39.745246
            ],
            [
              -75.044365,
              39.762032
            ],
            [
              -75.054462,
              39.782602
            ],
            [
              -75.063498,
              39.785957
            ],
            [
              -75.074413,
              39.773962
            ],
            [
              -75.08707,
              39.779576
            ],
            [
              -75.081939,
              39.79133
            ],
            [
              -75.070491,
              39.793597
            ],
            [
              -75.088723,
              39.814205
            ],
            [
              -75.083402,
              39.842369
            ],
            [
              -75.104648,
              39.862688
            ],
            [
              -75.118844,
              39.862761
            ],
            [
              -75.139019,
              39.887902
            ],
            [
              -75.129396,
              39.906629
            ],
            [
              -75.136316,
              39.945841
            ],
            [
              -75.127775,
              39.961522
            ],
            [
              -75.036354,
              39.996081
            ],
            [
              -75.010146,
              39.979768
            ],
            [
              -75.020165,
              39.968302
            ],
            [
              -75.013331,
              39.954201
            ]
          ]
        ]
      }
    },
    {
      "type": "Feature",
      "properties": {
        "GEOID": "34039",
        "NAME": "Union",
        "NAMELSAD": "Union County",
        "STATEFP": "34",
        "COUNTYFP": "039"
      },
      "geometry": {
        "type": "Polygon",
        "coordinates": [
          [
            [
              -74.200668,
              40.6329
            ],
            [
              -74.203291,
              40.593042
            ],
            [
              -74.21464,
              40.604149
            ],
            [
              -74.29099,
              40.591925
            ],
            [
              -74.305326,
              40.600586
            ],
            [
              -74.302921,
              40.608683
            ],
            [
              -74.463291,
              40.599187
            ],
            [
              -74.42435,
              40.619595
            ],
            [
              -74.401742,
              40.663303
            ],
            [
              -74.405499,
              40.667734
            ],
            [
              -74.420118,
              40.657637
            ],
            [
              -74.432773,
              40.664663
            ],
            [
              -74.450846,
              40.654148
            ],
            [
              -74.461035,
              40.673504
            ],
            [
              -74.402414,
              40.717929
            ],
            [
              -74.390854,
              40.718284
            ],
            [
              -74.371738,
              40.73964
            ],
            [
              -74.325596,
              40.717075
            ],
            [
              -74.303523,
              40.713188
            ],
            [
              -74.285525,
              40.722262
            ],
            [
              -74.221949,
              40.707341
            ],
            [
              -74.201547,
              40.686672
            ],
            [
              -74.16505,
              40.690161
            ],
            [
              -74.135775,
              40.675559
            ],
            [
              -74.161428,
              40.644148
            ],
            [
              -74.185641,
              40.646042
            ],
            [
              -74.200668,
              40.6329
            ]
          ]
        ]
      }
    },
    {
      "type": "Feature",
      "properties": {
        "GEOID": "34009",
        "NAME": "Cape May",
        "NAMELSAD": "Cape May County",
        "STATEFP": "34",
        "COUNTYFP": "009"
      },
      "geometry": {
        "type": "Polygon",
        "coordinates": [
          [
            [
              -74.540441,
              39.29945
            ],
            [
              -74.46493,
              39.29823
            ],
            [
              -74.565241,
              39.210642
            ],
            [
              -74.624602,
              39.14358
            ],
            [
              -74.644279,
              39.114824
            ],
            [
              -74.639868,
              39.094653
            ],
            [
              -74.646874,
              39.076212
            ],
            [
              -74.682193,
              39.049824
            ],
            [
              -74.715571,
              39.009216
            ],
            [
              -74.733423,
              38.967658
            ],
            [
              -74.773938,
              38.942794
            ],
            [
              -74.824329,
              38.896262
            ],
            [
              -74.907986,
              38.879316
            ],
            [
              -75.015123,
              38.788657
            ],
            [
              -75.168462,
              39.056179
            ],
            [
              -74.912237,
              39.17841
            ],
            [
              -74.926054,
              39.196889
            ],
            [
              -74.925736,
              39.218904
            ],
            [
              -74.896384,
              39.235054
            ],
            [
              -74.882146,
              39.30839
            ],
            [
              -74.864608,
              39.324373
            ],
            [
              -74.824937,
              39.305287
            ],
            [
              -74.784168,
              39.3073
            ],
            [
              -74.7789,
              39.298972
            ],
            [
              -74.719595,
              39.298644
            ],
            [
              -74.699051,
              39.289238
            ],
            [
              -74.676697,
              39.297365
            ],
            [
              -74.673362,
              39.2892
            ],
            [
              -74.668342,
              39.297735
            ],
            [
              -74.654238,
              39.288627
            ],
            [
              -74.641135,
              39.295912
            ],
            [
              -74.621465,
              39.292421
            ],
            [
              -74.588701,
              39.310074
            ],
            [
              -74.567213,
              39.298855
            ],
            [
              -74.540441,
              39.29945
            ]
          ]
        ]
      }
    },
    {
      "type": "Feature",
      "properties": {
        "GEOID": "34005",
        "NAME": "Burlington",
        "NAMELSAD": "Burlington County",
        "STATEFP": "34",
        "COUNTYFP": "005"
      },
      "geometry": {
        "type": "Polygon",
        "coordinates": [
          [
            [
              -74.470239,
              39.922527
            ],
            [
              -74.389708,
              39.773283
            ],
            [
              -74.390399,
              39.596037
            ],
            [
              -74.400819,
              39.572242
            ],
            [
              -74.419041,
              39.568367
            ],
            [
              -74.417393,
              39.557255
            ],
            [
              -74.438368,
              39.553519
            ],
            [
              -74.436119,
              39.541265
            ],
            [
              -74.445734,
              39.546352
            ],
            [
              -74.446257,
              39.558922
            ],
            [
              -74.45609,
              39.547269
            ],
            [
              -74.462997,
              39.556444
            ],
            [
              -74.493052,
              39.555627
            ],
            [
              -74.514793,
              39.574002
            ],
            [
              -74.525622,
              39.569355
            ],
            [
              -74.539701,
              39.574988
            ],
            [
              -74.553902,
              39.598406
            ],
            [
              -74.576655,
              39.598596
            ],
            [
              -74.621028,
              39.626691
            ],
            [
              -74.628775,
              39.620093
            ],
            [
              -74.634152,
              39.628073
            ],
            [
              -74.639484,
              39.622427
            ],
            [
              -74.654801,
              39.626846
            ],
            [
              -74.667851,
              39.683606
            ],
            [
              -74.772557,
              39.750636
            ],
            [
              -74.806856,
              39.783463
            ],
            [
              -74.843208,
              39.789919
            ],
            [
              -74.894822,
              39.783312
            ],
            [
              -74.902963,
              39.791108
            ],
            [
              -74.930745,
              39.885908
            ],
            [
              -74.949614,
              39.898338
            ],
            [
              -74.962871,
              39.920223
            ],
            [
              -74.983901,
              39.926826
            ],
            [
              -74.975708,
              39.939762
            ],
            [
              -75.015081,
              39.946813
            ],
            [
              -75.020165,
              39.968302
            ],
            [
              -75.010146,
              39.979768
            ],
            [
              -75.018875,
              39.989557
            ],
            [
              -75.036354,
              39.996081
            ],
            [
              -75.060639,
              39.99148
            ],
            [
              -75.048024,
              40.00972
            ],
            [
              -75.014864,
              40.019895
            ],
            [
              -74.938897,
              40.066099
            ],
            [
              -74.861756,
              40.083462
            ],
            [
              -74.835868,
              40.103466
            ],
            [
              -74.822531,
              40.126844
            ],
            [
              -74.784842,
              40.120388
            ],
            [
              -74.740555,
              40.135492
            ],
            [
              -74.706748,
              40.160997
            ],
            [
              -74.704213,
              40.168731
            ],
            [
              -74.710106,
              40.166724
            ],
            [
              -74.712812,
              40.175189
            ],
            [
              -74.700421,
              40.183651
            ],
            [
              -74.674436,
              40.173598
            ],
            [
              -74.677425,
              40.166069
            ],
            [
              -74.623517,
              40.149101
            ],
            [
              -74.621795,
              40.141123
            ],
            [
              -74.587835,
              40.138254
            ],
            [
              -74.470239,
              39.922527
            ]
          ]
        ]
      }
    },
    {
      "type": "Feature",
      "properties": {
        "GEOID": "34023",
        "NAME": "Middlesex",
        "NAMELSAD": "Middlesex County",
        "STATEFP": "34",
        "COUNTYFP": "023"
      },
      "geometry": {
        "type": "Polygon",
        "coordinates": [
          [
            [
              -74.526685,
              40.559487
            ],
            [
              -74.516228,
              40.581278
            ],
            [
              -74.466172,
              40.599094
            ],
            [
              -74.302921,
              40.608683
            ],
            [
              -74.305326,
              40.600586
            ],
            [
              -74.29099,
              40.591925
            ],
            [
              -74.21464,
              40.604149
            ],
            [
              -74.203291,
              40.593042
            ],
            [
              -74.214575,
              40.560533
            ],
            [
              -74.231415,
              40.559182
            ],
            [
              -74.250284,
              40.5423
            ],
            [
              -74.24602,
              40.520958
            ],
            [
              -74.258843,
              40.498875
            ],
            [
              -74.253036,
              40.48666
            ],
            [
              -74.228196,
              40.477621
            ],
            [
              -74.222709,
              40.451305
            ],
            [
              -74.247797,
              40.431197
            ],
            [
              -74.247894,
              40.406605
            ],
            [
              -74.377545,
              40.305432
            ],
            [
              -74.394231,
              40.28839
            ],
            [
              -74.393468,
              40.279524
            ],
            [
              -74.461017,
              40.251122
            ],
            [
              -74.484962,
              40.253325
            ],
            [
              -74.481991,
              40.273914
            ],
            [
              -74.522873,
              40.285608
            ],
            [
              -74.528142,
              40.2943
            ],
            [
              -74.556698,
              40.291656
            ],
            [
              -74.585587,
              40.313242
            ],
            [
              -74.622179,
              40.324502
            ],
            [
              -74.631011,
              40.340111
            ],
            [
              -74.62024,
              40.373749
            ],
            [
              -74.587865,
              40.394136
            ],
            [
              -74.584987,
              40.418176
            ],
            [
              -74.53619,
              40.438326
            ],
            [
              -74.482344,
              40.481751
            ],
            [
              -74.459863,
              40.491046
            ],
            [
              -74.466947,
              40.508898
            ],
            [
              -74.481902,
              40.512001
            ],
            [
              -74.526685,
              40.559487
            ]
          ]
        ]
      }
    },
    {
      "type": "Feature",
      "properties": {
        "GEOID": "34017",
        "NAME": "Hudson",
        "NAMELSAD": "Hudson County",
        "STATEFP": "34",
        "COUNTYFP": "017"
      },
      "geometry": {
        "type": "Polygon",
        "coordinates": [
          [
            [
              -74.020639,
              40.730391
            ],
            [
              -74.02639,
              40.700103
            ],
            [
              -74.055749,
              40.651476
            ],
            [
              -74.161428,
              40.644148
            ],
            [
              -74.112787,
              40.703102
            ],
            [
              -74.121387,
              40.721001
            ],
            [
              -74.117605,
              40.739638
            ],
            [
              -74.155687,
              40.733501
            ],
            [
              -74.163788,
              40.739201
            ],
            [
              -74.164513,
              40.756388
            ],
            [
              -74.147529,
              40.786491
            ],
            [
              -74.12719,
              40.771342
            ],
            [
              -74.100937,
              40.776017
            ],
            [
              -74.09027,
              40.76159
            ],
            [
              -74.089976,
              40.778176
            ],
            [
              -74.076753,
              40.795621
            ],
            [
              -74.01377,
              40.823059
            ],
            [
              -73.984739,
              40.797662
            ],
            [
              -74.014029,
              40.757551
            ],
            [
              -74.020639,
              40.730391
            ]
          ],
          [
            [
              -74.047207,
              40.690843
            ],
            [
              -74.047196,
              40.690795
            ],
            [
              -74.04719,
              40.690786
            ],
            [
              -74.047146,
              40.690715
            ],
            [
              -74.047048,
              40.690627
            ],
            [
              -74.047027,
              40.690589
            ],
            [
              -74.047031,
              40.69056
            ],
            [
              -74.047041,
              40.690483
            ],
            [
              -74.04715,
              40.690427
            ],
            [
              -74.047183,
              40.690411
            ],
            [
              -74.046922,
              40.690096
            ],
            [
              -74.046911,
              40.690082
            ],
            [
              -74.046485,
              40.689589
            ],
            [
              -74.046248,
              40.689319
            ],
            [
              -74.04537,
              40.688878
            ],
            [
              -74.045074,
              40.688735
            ],
            [
              -74.044792,
              40.68859
            ],
            [
              -74.044717,
              40.688576
            ],
            [
              -74.044445,
              40.688526
            ],
            [
              -74.044349,
              40.688508
            ],
            [
              -74.044132,
              40.688538
            ],
            [
              -74.043958,
              40.688567
            ],
            [
              -74.043942,
              40.688569
            ],
            [
              -74.043619,
              40.68876
            ],
            [
              -74.043499,
              40.689172
            ],
            [
              -74.043455,
              40.68963
            ],
            [
              -74.043863,
              40.690166
            ],
            [
              -74.043885,
              40.690185
            ],
            [
              -74.04457,
              40.690559
            ],
            [
              -74.045034,
              40.690731
            ],
            [
              -74.045427,
              40.690895
            ],
            [
              -74.04597,
              40.691103
            ],
            [
              -74.045982,
              40.691109
            ],
            [
              -74.046113,
              40.691125
            ],
            [
              -74.046143,
              40.691123
            ],
            [
              -74.046164,
              40.691098
            ],
            [
              -74.046177,
              40.691092
            ],
            [
              -74.046309,
              40.69109
            ],
            [
              -74.046487,
              40.691078
            ],
            [
              -74.046536,
              40.691076
            ],
            [
              -74.046965,
              40.691051
            ],
            [
              -74.047041,
              40.691041
            ],
            [
              -74.047099,
              40.691018
            ],
            [
              -74.047149,
              40.690985
            ],
            [
              -74.047187,
              40.690937
            ],
            [
              -74.047192,
              40.690926
            ],
            [
              -74.047207,
              40.690893
            ],
            [
              -74.047207,
              40.690843
            ]
          ],
          [
            [
              -74.04074,
              40.700131
            ],
            [
              -74.040719,
              40.700096
            ],
            [
              -74.040702,
              40.700071
            ],
            [
              -74.040691,
              40.70005
            ],
            [
              -74.040687,
              40.70001
            ],
            [
              -74.040684,
              40.699983
            ],
            [
              -74.040674,
              40.699962
            ],
            [
              -74.040674,
              40.699935
            ],
            [
              -74.040663,
              40.699907
            ],
            [
              -74.040644,
              40.699883
            ],
            [
              -74.040624,
              40.69986
            ],
            [
              -74.040615,
              40.699828
            ],
            [
              -74.040617,
              40.699803
            ],
            [
              -74.040612,
              40.699766
            ],
            [
              -74.0406,
              40.699739
            ],
            [
              -74.040578,
              40.69971
            ],
            [
              -74.040553,
              40.69968
            ],
            [
              -74.040531,
              40.699657
            ],
            [
              -74.040512,
              40.699627
            ],
            [
              -74.040484,
              40.699595
            ],
            [
              -74.04047,
              40.699558
            ],
            [
              -74.040466,
              40.699528
            ],
            [
              -74.040467,
              40.699493
            ],
            [
              -74.040455,
              40.699467
            ],
            [
              -74.040438,
              40.699438
            ],
            [
              -74.040426,
              40.699413
            ],
            [
              -74.040402,
              40.699393
            ],
            [
              -74.040351,
              40.699375
            ],
            [
              -74.040316,
              40.699365
            ],
            [
              -74.040278,
              40.699351
            ],
            [
              -74.040243,
              40.699333
            ],
            [
              -74.040211,
              40.699315
            ],
            [
              -74.04019,
              40.699278
            ],
            [
              -74.04019,
              40.699245
            ],
            [
              -74.040186,
              40.699215
            ],
            [
              -74.040158,
              40.699197
            ],
            [
              -74.04007,
              40.699172
            ],
            [
              -74.03998,
              40.699124
            ],
            [
              -74.039948,
              40.699098
            ],
            [
              -74.039899,
              40.699068
            ],
            [
              -74.039863,
              40.699045
            ],
            [
              -74.039846,
              40.699032
            ],
            [
              -74.039817,
              40.699009
            ],
            [
              -74.039796,
              40.698977
            ],
            [
              -74.039798,
              40.698937
            ],
            [
              -74.039824,
              40.698911
            ],
            [
              -74.039868,
              40.698893
            ],
            [
              -74.03991,
              40.698883
            ],
            [
              -74.039951,
              40.698882
            ],
            [
              -74.039986,
              40.698887
            ],
            [
              -74.040028,
              40.698898
            ],
            [
              -74.040044,
              40.698903
            ],
            [
              -74.040059,
              40.698907
            ],
            [
              -74.040096,
              40.698934
            ],
            [
              -74.040145,
              40.698897
            ],
            [
              -74.040215,
              40.698854
            ],
            [
              -74.040234,
              40.698833
            ],
            [
              -74.040078,
              40.698715
            ],
            [
              -74.039931,
              40.69859
            ],
            [
              -74.03967,
              40.698775
            ],
            [
              -74.039651,
              40.698795
            ],
            [
              -74.039632,
              40.69879
            ],
            [
              -74.039585,
              40.69879
            ],
            [
              -74.039538,
              40.698787
            ],
            [
              -74.039508,
              40.69878
            ],
            [
              -74.039488,
              40.698777
            ],
            [
              -74.039469,
              40.698752
            ],
            [
              -74.039438,
              40.698739
            ],
            [
              -74.039411,
              40.698737
            ],
            [
              -74.039376,
              40.698731
            ],
            [
              -74.039365,
              40.698709
            ],
            [
              -74.039341,
              40.698684
            ],
            [
              -74.039317,
              40.698665
            ],
            [
              -74.039285,
              40.698632
            ],
            [
              -74.039245,
              40.698614
            ],
            [
              -74.039205,
              40.698604
            ],
            [
              -74.039168,
              40.698595
            ],
            [
              -74.039115,
              40.698592
            ],
            [
              -74.039061,
              40.698597
            ],
            [
              -74.039006,
              40.698594
            ],
            [
              -74.03896,
              40.698595
            ],
            [
              -74.038925,
              40.698607
            ],
            [
              -74.038879,
              40.698611
            ],
            [
              -74.038827,
              40.698624
            ],
            [
              -74.03878,
              40.698636
            ],
            [
              -74.038744,
              40.698637
            ],
            [
              -74.038712,
              40.698654
            ],
            [
              -74.038681,
              40.69866
            ],
            [
              -74.038653,
              40.698663
            ],
            [
              -74.038634,
              40.698667
            ],
            [
              -74.038621,
              40.698671
            ],
            [
              -74.038603,
              40.698677
            ],
            [
              -74.038623,
              40.698698
            ],
            [
              -74.038606,
              40.698718
            ],
            [
              -74.038569,
              40.69873
            ],
            [
              -74.038527,
              40.698712
            ],
            [
              -74.038505,
              40.698702
            ],
            [
              -74.038453,
              40.698681
            ],
            [
              -74.03842,
              40.698665
            ],
            [
              -74.038392,
              40.698666
            ],
            [
              -74.038372,
              40.698669
            ],
            [
              -74.038368,
              40.698687
            ],
            [
              -74.03838,
              40.698714
            ],
            [
              -74.038396,
              40.698729
            ],
            [
              -74.038435,
              40.698792
            ],
            [
              -74.038455,
              40.698825
            ],
            [
              -74.038467,
              40.69887
            ],
            [
              -74.038463,
              40.698924
            ],
            [
              -74.038459,
              40.698981
            ],
            [
              -74.038467,
              40.699017
            ],
            [
              -74.038498,
              40.699074
            ],
            [
              -74.038494,
              40.699115
            ],
            [
              -74.03851,
              40.699147
            ],
            [
              -74.038533,
              40.699172
            ],
            [
              -74.038561,
              40.699193
            ],
            [
              -74.038598,
              40.69921
            ],
            [
              -74.038632,
              40.699239
            ],
            [
              -74.038664,
              40.699263
            ],
            [
              -74.038697,
              40.699279
            ],
            [
              -74.038723,
              40.699302
            ],
            [
              -74.038742,
              40.699335
            ],
            [
              -74.038759,
              40.699368
            ],
            [
              -74.038772,
              40.699398
            ],
            [
              -74.038783,
              40.699406
            ],
            [
              -74.038796,
              40.699439
            ],
            [
              -74.038802,
              40.699487
            ],
            [
              -74.038815,
              40.699532
            ],
            [
              -74.038838,
              40.699562
            ],
            [
              -74.03888,
              40.699602
            ],
            [
              -74.038893,
              40.699625
            ],
            [
              -74.038936,
              40.699655
            ],
            [
              -74.03899,
              40.699662
            ],
            [
              -74.039024,
              40.699662
            ],
            [
              -74.039075,
              40.699668
            ],
            [
              -74.039121,
              40.699671
            ],
            [
              -74.039163,
              40.699677
            ],
            [
              -74.039255,
              40.699687
            ],
            [
              -74.039287,
              40.699708
            ],
            [
              -74.03933,
              40.699727
            ],
            [
              -74.039381,
              40.69975
            ],
            [
              -74.039428,
              40.699763
            ],
            [
              -74.039477,
              40.699782
            ],
            [
              -74.039511,
              40.699816
            ],
            [
              -74.039547,
              40.699843
            ],
            [
              -74.039586,
              40.699853
            ],
            [
              -74.039622,
              40.699856
            ],
            [
              -74.039665,
              40.699873
            ],
            [
              -74.039689,
              40.699899
            ],
            [
              -74.039713,
              40.699928
            ],
            [
              -74.039745,
              40.69995
            ],
            [
              -74.039783,
              40.699952
            ],
            [
              -74.039825,
              40.699955
            ],
            [
              -74.039859,
              40.699966
            ],
            [
              -74.0399,
              40.699981
            ],
            [
              -74.039934,
              40.699994
            ],
            [
              -74.039966,
              40.700018
            ],
            [
              -74.039994,
              40.700041
            ],
            [
              -74.040022,
              40.700061
            ],
            [
              -74.040048,
              40.700074
            ],
            [
              -74.040082,
              40.700092
            ],
            [
              -74.040121,
              40.700101
            ],
            [
              -74.040153,
              40.700103
            ],
            [
              -74.040187,
              40.700114
            ],
            [
              -74.040249,
              40.700117
            ],
            [
              -74.040283,
              40.700111
            ],
            [
              -74.040329,
              40.700101
            ],
            [
              -74.040376,
              40.700112
            ],
            [
              -74.040415,
              40.700126
            ],
            [
              -74.04046,
              40.700149
            ],
            [
              -74.040496,
              40.700162
            ],
            [
              -74.040528,
              40.700176
            ],
            [
              -74.040569,
              40.700188
            ],
            [
              -74.040612,
              40.700201
            ],
            [
              -74.040648,
              40.700214
            ],
            [
              -74.040697,
              40.700215
            ],
            [
              -74.04073,
              40.700193
            ],
            [
              -74.040747,
              40.700167
            ],
            [
              -74.04074,
              40.700131
            ]
          ]
        ]
      }
    },
    {
      "type": "Feature",
      "properties": {
        "GEOID": "34025",
        "NAME": "Monmouth",
        "NAMELSAD": "Monmouth County",
        "STATEFP": "34",
        "COUNTYFP": "025"
      },
      "geometry": {
        "type": "Polygon",
        "coordinates": [
          [
            [
              -74.038643,
              40.104456
            ],
            [
              -74.072373,
              40.089381
            ],
            [
              -74.094222,
              40.107509
            ],
            [
              -74.095727,
              40.12853
            ],
            [
              -74.107464,
              40.137036
            ],
            [
              -74.150315,
              40.098877
            ],
            [
              -74.17873,
              40.110942
            ],
            [
              -74.230634,
              40.109561
            ],
            [
              -74.243744,
              40.116099
            ],
            [
              -74.241786,
              40.130888
            ],
            [
              -74.259811,
              40.149052
            ],
            [
              -74.261455,
              40.167033
            ],
            [
              -74.40671,
              40.172402
            ],
            [
              -74.553105,
              40.07913
            ],
            [
              -74.614576,
              40.182383
            ],
            [
              -74.571241,
              40.185293
            ],
            [
              -74.543268,
              40.216692
            ],
            [
              -74.481476,
              40.24289
            ],
            [
              -74.487407,
              40.253129
            ],
            [
              -74.461017,
              40.251122
            ],
            [
              -74.393468,
              40.279524
            ],
            [
              -74.394231,
              40.28839
            ],
            [
              -74.377545,
              40.305432
            ],
            [
              -74.247894,
              40.406605
            ],
            [
              -74.247797,
              40.431197
            ],
            [
              -74.223084,
              40.449674
            ],
            [
              -74.228196,
              40.477621
            ],
            [
              -73.977874,
              40.519095
            ],
            [
              -73.888434,
              40.484049
            ],
            [
              -73.890791,
              40.31069
            ],
            [
              -73.898208,
              40.274353
            ],
            [
              -73.962735,
              40.119914
            ],
            [
              -73.965414,
              40.097642
            ],
            [
              -74.038643,
              40.104456
            ]
          ]
        ]
      }
    },
    {
      "type": "Feature",
      "properties": {
        "GEOID": "34035",
        "NAME": "Somerset",
        "NAMELSAD": "Somerset County",
        "STATEFP": "34",
        "COUNTYFP": "035"
      },
      "geometry": {
        "type": "Polygon",
        "coordinates": [
          [
            [
              -74.413802,
              40.64101
            ],
            [
              -74.41623,
              40.629281
            ],
            [
              -74.436867,
              40.610525
            ],
            [
              -74.516149,
              40.581327
            ],
            [
              -74.525886,
              40.568387
            ],
            [
              -74.514122,
              40.542031
            ],
            [
              -74.481902,
              40.512001
            ],
            [
              -74.466947,
              40.508898
            ],
            [
              -74.459863,
              40.491046
            ],
            [
              -74.482344,
              40.481751
            ],
            [
              -74.53619,
              40.438326
            ],
            [
              -74.584987,
              40.418176
            ],
            [
              -74.587865,
              40.394136
            ],
            [
              -74.612611,
              40.375915
            ],
            [
              -74.653928,
              40.391048
            ],
            [
              -74.722061,
              40.375205
            ],
            [
              -74.797881,
              40.51567
            ],
            [
              -74.775979,
              40.503606
            ],
            [
              -74.712962,
              40.584231
            ],
            [
              -74.724937,
              40.588755
            ],
            [
              -74.721752,
              40.600702
            ],
            [
              -74.702703,
              40.621117
            ],
            [
              -74.727646,
              40.635989
            ],
            [
              -74.71952,
              40.654324
            ],
            [
              -74.730802,
              40.665457
            ],
            [
              -74.722701,
              40.67009
            ],
            [
              -74.717728,
              40.683869
            ],
            [
              -74.723925,
              40.688151
            ],
            [
              -74.715759,
              40.700295
            ],
            [
              -74.725666,
              40.719532
            ],
            [
              -74.556018,
              40.758288
            ],
            [
              -74.54935,
              40.733853
            ],
            [
              -74.530893,
              40.729854
            ],
            [
              -74.526198,
              40.709441
            ],
            [
              -74.513875,
              40.701097
            ],
            [
              -74.516762,
              40.68925
            ],
            [
              -74.527879,
              40.684344
            ],
            [
              -74.525718,
              40.670487
            ],
            [
              -74.534373,
              40.667247
            ],
            [
              -74.523633,
              40.649422
            ],
            [
              -74.461035,
              40.673504
            ],
            [
              -74.450846,
              40.654148
            ],
            [
              -74.429866,
              40.664993
            ],
            [
              -74.419894,
              40.65766
            ],
            [
              -74.404711,
              40.667571
            ],
            [
              -74.403404,
              40.653834
            ],
            [
              -74.413802,
              40.64101
            ]
          ]
        ]
      }
    },
    {
      "type": "Feature",
      "properties": {
        "GEOID": "34029",
        "NAME": "Ocean",
        "NAMELSAD": "Ocean County",
        "STATEFP": "34",
        "COUNTYFP": "029"
      },
      "geometry": {
        "type": "Polygon",
        "coordinates": [
          [
            [
              -74.416891,
              39.822682
            ],
            [
              -74.553105,
              40.07913
            ],
            [
              -74.40671,
              40.172402
            ],
            [
              -74.261455,
              40.167033
            ],
            [
              -74.259811,
              40.149052
            ],
            [
              -74.241786,
              40.130888
            ],
            [
              -74.243744,
              40.116099
            ],
            [
              -74.230634,
              40.109561
            ],
            [
              -74.17873,
              40.110942
            ],
            [
              -74.150315,
              40.098877
            ],
            [
              -74.107464,
              40.137036
            ],
            [
              -74.095727,
              40.12853
            ],
            [
              -74.094222,
              40.107509
            ],
            [
              -74.072373,
              40.089381
            ],
            [
              -74.045719,
              40.105295
            ],
            [
              -73.965414,
              40.097642
            ],
            [
              -73.999577,
              39.976798
            ],
            [
              -74.043863,
              39.736353
            ],
            [
              -74.096531,
              39.649949
            ],
            [
              -74.232062,
              39.475198
            ],
            [
              -74.296461,
              39.475292
            ],
            [
              -74.312612,
              39.500117
            ],
            [
              -74.326382,
              39.506332
            ],
            [
              -74.380796,
              39.498537
            ],
            [
              -74.402431,
              39.539111
            ],
            [
              -74.416661,
              39.550536
            ],
            [
              -74.419041,
              39.568367
            ],
            [
              -74.400819,
              39.572242
            ],
            [
              -74.390399,
              39.596037
            ],
            [
              -74.389708,
              39.773283
            ],
            [
              -74.416891,
              39.822682
            ]
          ]
        ]
      }
    },
    {
      "type": "Feature",
      "properties": {
        "GEOID": "34015",
        "NAME": "Gloucester",
        "NAMELSAD": "Gloucester County",
        "STATEFP": "34",
        "COUNTYFP": "015"
      },
      "geometry": {
        "type": "Polygon",
        "coordinates": [
          [
            [
              -75.11506,
              39.861534
            ],
            [
              -75.104648,
              39.862688
            ],
            [
              -75.083269,
              39.84209
            ],
            [
              -75.088723,
              39.814205
            ],
            [
              -75.070491,
              39.793597
            ],
            [
              -75.081939,
              39.79133
            ],
            [
              -75.08707,
              39.779576
            ],
            [
              -75.074413,
              39.773962
            ],
            [
              -75.063498,
              39.785957
            ],
            [
              -75.054462,
              39.782602
            ],
            [
              -75.044365,
              39.762032
            ],
            [
              -75.021309,
              39.745246
            ],
            [
              -75.024252,
              39.730582
            ],
            [
              -74.987551,
              39.706701
            ],
            [
              -74.930607,
              39.690869
            ],
            [
              -74.908883,
              39.665351
            ],
            [
              -74.902725,
              39.631879
            ],
            [
              -74.87726,
              39.608352
            ],
            [
              -74.985271,
              39.514967
            ],
            [
              -75.199793,
              39.666996
            ],
            [
              -75.234857,
              39.661619
            ],
            [
              -75.247542,
              39.664523
            ],
            [
              -75.253461,
              39.679103
            ],
            [
              -75.326343,
              39.690015
            ],
            [
              -75.336052,
              39.70388
            ],
            [
              -75.376589,
              39.726421
            ],
            [
              -75.376758,
              39.744944
            ],
            [
              -75.392534,
              39.750416
            ],
            [
              -75.389857,
              39.760464
            ],
            [
              -75.405959,
              39.763484
            ],
            [
              -75.394971,
              39.773732
            ],
            [
              -75.407712,
              39.787445
            ],
            [
              -75.429061,
              39.78382
            ],
            [
              -75.404274,
              39.795567
            ],
            [
              -75.415022,
              39.802004
            ],
            [
              -75.330432,
              39.849013
            ],
            [
              -75.246149,
              39.853982
            ],
            [
              -75.187661,
              39.880458
            ],
            [
              -75.139019,
              39.887902
            ],
            [
              -75.11506,
              39.861534
            ]
          ]
        ]
      }
    },
    {
      "type": "Feature",
      "properties": {
        "GEOID": "34011",
        "NAME": "Cumberland",
        "NAMELSAD": "Cumberland County",
        "STATEFP": "34",
        "COUNTYFP": "011"
      },
      "geometry": {
        "type": "Polygon",
        "coordinates": [
          [
            [
              -75.418723,
              39.432496
            ],
            [
              -75.40964,
              39.436716
            ],
            [
              -75.416743,
              39.439114
            ],
            [
              -75.409434,
              39.442554
            ],
            [
              -75.414691,
              39.452259
            ],
            [
              -75.407786,
              39.458718
            ],
            [
              -75.368213,
              39.456479
            ],
            [
              -75.342376,
              39.490622
            ],
            [
              -75.31802,
              39.49204
            ],
            [
              -75.238434,
              39.559039
            ],
            [
              -75.083339,
              39.45753
            ],
            [
              -75.073179,
              39.485314
            ],
            [
              -75.079769,
              39.501178
            ],
            [
              -75.074478,
              39.544511
            ],
            [
              -75.061854,
              39.568746
            ],
            [
              -74.855978,
              39.424238
            ],
            [
              -74.851968,
              39.376587
            ],
            [
              -74.864932,
              39.338794
            ],
            [
              -74.861294,
              39.323815
            ],
            [
              -74.882146,
              39.30839
            ],
            [
              -74.896384,
              39.235054
            ],
            [
              -74.925736,
              39.218904
            ],
            [
              -74.926054,
              39.196889
            ],
            [
              -74.912237,
              39.17841
            ],
            [
              -75.168462,
              39.056179
            ],
            [
              -75.321021,
              39.251379
            ],
            [
              -75.444751,
              39.355089
            ],
            [
              -75.406685,
              39.380295
            ],
            [
              -75.417999,
              39.394316
            ],
            [
              -75.407456,
              39.395951
            ],
            [
              -75.405069,
              39.407226
            ],
            [
              -75.413691,
              39.404529
            ],
            [
              -75.419558,
              39.412174
            ],
            [
              -75.408276,
              39.425095
            ],
            [
              -75.418723,
              39.432496
            ]
          ]
        ]
      }
    },
    {
      "type": "Feature",
      "properties": {
        "GEOID": "34027",
        "NAME": "Morris",
        "NAMELSAD": "Morris County",
        "STATEFP": "34",
        "COUNTYFP": "027"
      },
      "geometry": {
        "type": "Polygon",
        "coordinates": [
          [
            [
              -74.430172,
              41.020174
            ],
            [
              -74.418876,
              41.028729
            ],
            [
              -74.387291,
              41.011693
            ],
            [
              -74.355474,
              41.013911
            ],
            [
              -74.350189,
              41.003975
            ],
            [
              -74.336649,
              41.007604
            ],
            [
              -74.309494,
              40.998409
            ],
            [
              -74.298907,
              41.002952
            ],
            [
              -74.292833,
              40.987955
            ],
            [
              -74.297669,
              40.979912
            ],
            [
              -74.277508,
              40.97355
            ],
            [
              -74.288496,
              40.924788
            ],
            [
              -74.266597,
              40.908609
            ],
            [
              -74.273507,
              40.906546
            ],
            [
              -74.271975,
              40.897321
            ],
            [
              -74.284136,
              40.894816
            ],
            [
              -74.281848,
              40.90081
            ],
            [
              -74.292645,
              40.905856
            ],
            [
              -74.334294,
              40.90546
            ],
            [
              -74.337211,
              40.866867
            ],
            [
              -74.31734,
              40.864009
            ],
            [
              -74.330364,
              40.848687
            ],
            [
              -74.325473,
              40.843371
            ],
            [
              -74.334987,
              40.817052
            ],
            [
              -74.367062,
              40.793286
            ],
            [
              -74.370599,
              40.764276
            ],
            [
              -74.377409,
              40.761386
            ],
            [
              -74.357618,
              40.754454
            ],
            [
              -74.390854,
              40.718284
            ],
            [
              -74.402323,
              40.717984
            ],
            [
              -74.451593,
              40.685703
            ],
            [
              -74.454183,
              40.674088
            ],
            [
              -74.523633,
              40.649422
            ],
            [
              -74.534373,
              40.667247
            ],
            [
              -74.525718,
              40.670487
            ],
            [
              -74.527879,
              40.684344
            ],
            [
              -74.516762,
              40.68925
            ],
            [
              -74.513875,
              40.701097
            ],
            [
              -74.526198,
              40.709441
            ],
            [
              -74.530893,
              40.729854
            ],
            [
              -74.54935,
              40.733853
            ],
            [
              -74.556018,
              40.758288
            ],
            [
              -74.732704,
              40.720082
            ],
            [
              -74.770989,
              40.736048
            ],
            [
              -74.823631,
              40.74221
            ],
            [
              -74.889819,
              40.787729
            ],
            [
              -74.850513,
              40.803956
            ],
            [
              -74.81861,
              40.836485
            ],
            [
              -74.821579,
              40.849184
            ],
            [
              -74.801942,
              40.863898
            ],
            [
              -74.807368,
              40.881715
            ],
            [
              -74.77896,
              40.906425
            ],
            [
              -74.731928,
              40.920852
            ],
            [
              -74.711383,
              40.899169
            ],
            [
              -74.653214,
              40.921313
            ],
            [
              -74.653085,
              40.929644
            ],
            [
              -74.63644,
              40.942638
            ],
            [
              -74.64156,
              40.962199
            ],
            [
              -74.632378,
              40.973717
            ],
            [
              -74.503212,
              41.085873
            ],
            [
              -74.486835,
              41.076445
            ],
            [
              -74.498989,
              41.035008
            ],
            [
              -74.446914,
              41.054426
            ],
            [
              -74.427033,
              41.036178
            ],
            [
              -74.430172,
              41.020174
            ]
          ]
        ]
      }
    },
    {
      "type": "Feature",
      "properties": {
        "GEOID": "34013",
        "NAME": "Essex",
        "NAMELSAD": "Essex County",
        "STATEFP": "34",
        "COUNTYFP": "013"
      },
      "geometry": {
        "type": "Polygon",
        "coordinates": [
          [
            [
              -74.139575,
              40.805409
            ],
            [
              -74.166087,
              40.747402
            ],
            [
              -74.155687,
              40.733501
            ],
            [
              -74.117605,
              40.739638
            ],
            [
              -74.121387,
              40.721001
            ],
            [
              -74.112787,
              40.703102
            ],
            [
              -74.136557,
              40.674368
            ],
            [
              -74.16505,
              40.690161
            ],
            [
              -74.201547,
              40.686672
            ],
            [
              -74.221949,
              40.707341
            ],
            [
              -74.285525,
              40.722262
            ],
            [
              -74.303523,
              40.713188
            ],
            [
              -74.325596,
              40.717075
            ],
            [
              -74.371738,
              40.73964
            ],
            [
              -74.357547,
              40.754788
            ],
            [
              -74.377409,
              40.761386
            ],
            [
              -74.370608,
              40.764249
            ],
            [
              -74.364247,
              40.799082
            ],
            [
              -74.334987,
              40.817052
            ],
            [
              -74.325473,
              40.843371
            ],
            [
              -74.330364,
              40.848687
            ],
            [
              -74.318916,
              40.858814
            ],
            [
              -74.318672,
              40.865954
            ],
            [
              -74.338244,
              40.869881
            ],
            [
              -74.339107,
              40.894404
            ],
            [
              -74.330458,
              40.90867
            ],
            [
              -74.292421,
              40.905804
            ],
            [
              -74.281809,
              40.900759
            ],
            [
              -74.284464,
              40.894895
            ],
            [
              -74.270234,
              40.896807
            ],
            [
              -74.259813,
              40.883769
            ],
            [
              -74.196999,
              40.859464
            ],
            [
              -74.130259,
              40.820185
            ],
            [
              -74.139575,
              40.805409
            ]
          ]
        ]
      }
    },
    {
      "type": "Feature",
      "properties": {
        "GEOID": "34003",
        "NAME": "Bergen",
        "NAMELSAD": "Bergen County",
        "STATEFP": "34",
        "COUNTYFP": "003"
      },
      "geometry": {
        "type": "Polygon",
        "coordinates": [
          [
            [
              -73.998303,
              40.808477
            ],
            [
              -74.017031,
              40.823577
            ],
            [
              -74.035823,
              40.808103
            ],
            [
              -74.062705,
              40.804796
            ],
            [
              -74.089143,
              40.779596
            ],
            [
              -74.09027,
              40.76159
            ],
            [
              -74.100937,
              40.776017
            ],
            [
              -74.12719,
              40.771342
            ],
            [
              -74.147529,
              40.786491
            ],
            [
              -74.137005,
              40.817337
            ],
            [
              -74.122611,
              40.825042
            ],
            [
              -74.121114,
              40.857897
            ],
            [
              -74.106786,
              40.859299
            ],
            [
              -74.130315,
              40.885486
            ],
            [
              -74.129408,
              40.920213
            ],
            [
              -74.140403,
              40.924201
            ],
            [
              -74.148163,
              40.942074
            ],
            [
              -74.141048,
              40.966348
            ],
            [
              -74.170275,
              40.983904
            ],
            [
              -74.171141,
              40.977066
            ],
            [
              -74.224533,
              40.981303
            ],
            [
              -74.248532,
              40.992094
            ],
            [
              -74.272226,
              41.017935
            ],
            [
              -74.211224,
              41.133714
            ],
            [
              -73.893628,
              40.997165
            ],
            [
              -73.929821,
              40.888682
            ],
            [
              -73.963577,
              40.826642
            ],
            [
              -73.984739,
              40.797662
            ],
            [
              -73.998303,
              40.808477
            ]
          ]
        ]
      }
    },
    {
      "type": "Feature",
      "properties": {
        "GEOID": "34041",
        "NAME": "Warren",
        "NAMELSAD": "Warren County",
        "STATEFP": "34",
        "COUNTYFP": "041"
      },
      "geometry": {
        "type": "Polygon",
        "coordinates": [
          [
            [
              -74.983388,
              40.705372
            ],
            [
              -75.048836,
              40.67964
            ],
            [
              -75.108451,
              40.639569
            ],
            [
              -75.145669,
              40.628802
            ],
            [
              -75.185185,
              40.592332
            ],
            [
              -75.201348,
              40.614628
            ],
            [
              -75.188595,
              40.623636
            ],
            [
              -75.200452,
              40.649219
            ],
            [
              -75.176803,
              40.675715
            ],
            [
              -75.196921,
              40.681297
            ],
            [
              -75.203921,
              40.691498
            ],
            [
              -75.182084,
              40.731522
            ],
            [
              -75.196535,
              40.751631
            ],
            [
              -75.17904,
              40.761897
            ],
            [
              -75.171587,
              40.777745
            ],
            [
              -75.1344,
              40.77377
            ],
            [
              -75.108505,
              40.791094
            ],
            [
              -75.083929,
              40.824471
            ],
            [
              -75.095784,
              40.847082
            ],
            [
              -75.066008,
              40.847594
            ],
            [
              -75.051029,
              40.865662
            ],
            [
              -75.075345,
              40.894166
            ],
            [
              -75.079295,
              40.91388
            ],
            [
              -75.117767,
              40.953013
            ],
            [
              -75.120232,
              40.968702
            ],
            [
              -75.134701,
              40.972038
            ],
            [
              -75.131341,
              40.98998
            ],
            [
              -75.027102,
              41.039529
            ],
            [
              -75.012485,
              41.067197
            ],
            [
              -74.970987,
              41.085293
            ],
            [
              -74.966906,
              41.09441
            ],
            [
              -74.769425,
              40.910934
            ],
            [
              -74.806127,
              40.883723
            ],
            [
              -74.80299,
              40.861741
            ],
            [
              -74.821382,
              40.849454
            ],
            [
              -74.818527,
              40.836619
            ],
            [
              -74.842469,
              40.811641
            ],
            [
              -74.904156,
              40.781032
            ],
            [
              -74.903134,
              40.771386
            ],
            [
              -74.96845,
              40.710753
            ],
            [
              -74.983388,
              40.705372
            ]
          ]
        ]
      }
    },
    {
      "type": "Feature",
      "properties": {
        "GEOID": "34031",
        "NAME": "Passaic",
        "NAMELSAD": "Passaic County",
        "STATEFP": "34",
        "COUNTYFP": "031"
      },
      "geometry": {
        "type": "Polygon",
        "coordinates": [
          [
            [
              -74.270658,
              41.021033
            ],
            [
              -74.248532,
              40.992094
            ],
            [
              -74.224533,
              40.981303
            ],
            [
              -74.171141,
              40.977066
            ],
            [
              -74.170275,
              40.983904
            ],
            [
              -74.141048,
              40.966348
            ],
            [
              -74.148163,
              40.942074
            ],
            [
              -74.140403,
              40.924201
            ],
            [
              -74.129408,
              40.920213
            ],
            [
              -74.130315,
              40.885486
            ],
            [
              -74.106969,
              40.8616
            ],
            [
              -74.109661,
              40.855272
            ],
            [
              -74.121168,
              40.857799
            ],
            [
              -74.125201,
              40.8216
            ],
            [
              -74.264289,
              40.886906
            ],
            [
              -74.272903,
              40.899073
            ],
            [
              -74.266977,
              40.910435
            ],
            [
              -74.288511,
              40.924833
            ],
            [
              -74.277508,
              40.97355
            ],
            [
              -74.297669,
              40.979912
            ],
            [
              -74.292833,
              40.987955
            ],
            [
              -74.298851,
              41.002913
            ],
            [
              -74.309494,
              40.998409
            ],
            [
              -74.336649,
              41.007604
            ],
            [
              -74.350189,
              41.003975
            ],
            [
              -74.355474,
              41.013911
            ],
            [
              -74.387291,
              41.011693
            ],
            [
              -74.418876,
              41.028729
            ],
            [
              -74.43504,
              41.020021
            ],
            [
              -74.426943,
              41.035981
            ],
            [
              -74.446914,
              41.054426
            ],
            [
              -74.497634,
              41.034116
            ],
            [
              -74.501692,
              41.042098
            ],
            [
              -74.486835,
              41.076445
            ],
            [
              -74.503212,
              41.085873
            ],
            [
              -74.36751,
              41.203241
            ],
            [
              -74.211224,
              41.133714
            ],
            [
              -74.270658,
              41.021033
            ]
          ]
        ]
      }
    },
    {
      "type": "Feature",
      "properties": {
        "GEOID": "34033",
        "NAME": "Salem",
        "NAMELSAD": "Salem County",
        "STATEFP": "34",
        "COUNTYFP": "033"
      },
      "geometry": {
        "type": "Polygon",
        "coordinates": [
          [
            [
              -75.307177,
              39.501261
            ],
            [
              -75.326089,
              39.488494
            ],
            [
              -75.342376,
              39.490622
            ],
            [
              -75.368213,
              39.456479
            ],
            [
              -75.39983,
              39.462271
            ],
            [
              -75.413859,
              39.453663
            ],
            [
              -75.409212,
              39.443057
            ],
            [
              -75.416598,
              39.438474
            ],
            [
              -75.409389,
              39.437544
            ],
            [
              -75.418821,
              39.432301
            ],
            [
              -75.408174,
              39.424279
            ],
            [
              -75.419407,
              39.411212
            ],
            [
              -75.405096,
              39.405544
            ],
            [
              -75.407456,
              39.395951
            ],
            [
              -75.417999,
              39.394316
            ],
            [
              -75.406685,
              39.380295
            ],
            [
              -75.444751,
              39.355089
            ],
            [
              -75.560538,
              39.455645
            ],
            [
              -75.55909,
              39.495806
            ],
            [
              -75.526974,
              39.499168
            ],
            [
              -75.526787,
              39.53144
            ],
            [
              -75.534014,
              39.540702
            ],
            [
              -75.51196,
              39.56729
            ],
            [
              -75.514747,
              39.580884
            ],
            [
              -75.553512,
              39.601819
            ],
            [
              -75.558773,
              39.629987
            ],
            [
              -75.515533,
              39.666326
            ],
            [
              -75.509874,
              39.693915
            ],
            [
              -75.488384,
              39.714708
            ],
            [
              -75.476481,
              39.716142
            ],
            [
              -75.463921,
              39.760763
            ],
            [
              -75.4383,
              39.784402
            ],
            [
              -75.405489,
              39.796368
            ],
            [
              -75.429061,
              39.78382
            ],
            [
              -75.407712,
              39.787445
            ],
            [
              -75.394971,
              39.773732
            ],
            [
              -75.405959,
              39.763484
            ],
            [
              -75.389857,
              39.760464
            ],
            [
              -75.392534,
              39.750416
            ],
            [
              -75.376758,
              39.744944
            ],
            [
              -75.376589,
              39.726421
            ],
            [
              -75.336052,
              39.70388
            ],
            [
              -75.326343,
              39.690015
            ],
            [
              -75.253461,
              39.679103
            ],
            [
              -75.247542,
              39.664523
            ],
            [
              -75.234857,
              39.661619
            ],
            [
              -75.199793,
              39.666996
            ],
            [
              -75.061854,
              39.568746
            ],
            [
              -75.074478,
              39.544511
            ],
            [
              -75.079769,
              39.501178
            ],
            [
              -75.073179,
              39.485314
            ],
            [
              -75.083823,
              39.457354
            ],
            [
              -75.238434,
              39.559039
            ],
            [
              -75.307177,
              39.501261
            ]
          ]
        ]
      }
    },
    {
      "type": "Feature",
      "properties": {
        "GEOID": "34019",
        "NAME": "Hunterdon",
        "NAMELSAD": "Hunterdon County",
        "STATEFP": "34",
        "COUNTYFP": "019"
      },
      "geometry": {
        "type": "Polygon",
        "coordinates": [
          [
            [
              -75.109046,
              40.642163
            ],
            [
              -75.048836,
              40.67964
            ],
            [
              -74.968927,
              40.710392
            ],
            [
              -74.902718,
              40.771836
            ],
            [
              -74.904481,
              40.780755
            ],
            [
              -74.889819,
              40.787729
            ],
            [
              -74.823631,
              40.74221
            ],
            [
              -74.770989,
              40.736048
            ],
            [
              -74.724378,
              40.719439
            ],
            [
              -74.715759,
              40.700295
            ],
            [
              -74.723925,
              40.688151
            ],
            [
              -74.717728,
              40.683869
            ],
            [
              -74.722701,
              40.67009
            ],
            [
              -74.730802,
              40.665457
            ],
            [
              -74.71952,
              40.654324
            ],
            [
              -74.727646,
              40.635989
            ],
            [
              -74.702703,
              40.621117
            ],
            [
              -74.721752,
              40.600702
            ],
            [
              -74.724937,
              40.588755
            ],
            [
              -74.712962,
              40.584231
            ],
            [
              -74.775979,
              40.503606
            ],
            [
              -74.797881,
              40.51567
            ],
            [
              -74.748147,
              40.424156
            ],
            [
              -74.80847,
              40.416664
            ],
            [
              -74.802016,
              40.384972
            ],
            [
              -74.869678,
              40.377774
            ],
            [
              -74.856262,
              40.346696
            ],
            [
              -74.942909,
              40.341683
            ],
            [
              -74.966969,
              40.398475
            ],
            [
              -74.99586,
              40.410384
            ],
            [
              -75.028633,
              40.403971
            ],
            [
              -75.060065,
              40.420319
            ],
            [
              -75.070678,
              40.456794
            ],
            [
              -75.062664,
              40.480439
            ],
            [
              -75.068581,
              40.542185
            ],
            [
              -75.115536,
              40.57286
            ],
            [
              -75.140172,
              40.57537
            ],
            [
              -75.171623,
              40.564222
            ],
            [
              -75.194937,
              40.577142
            ],
            [
              -75.1896,
              40.591776
            ],
            [
              -75.161676,
              40.617949
            ],
            [
              -75.109046,
              40.642163
            ]
          ]
        ]
      }
    },
    {
      "type": "Feature",
      "properties": {
        "GEOID": "34001",
        "NAME": "Atlantic",
        "NAMELSAD": "Atlantic County",
        "STATEFP": "34",
        "COUNTYFP": "001"
      },
      "geometry": {
        "type": "Polygon",
        "coordinates": [
          [
            [
              -74.586396,
              39.309895
            ],
            [
              -74.621465,
              39.292421
            ],
            [
              -74.641135,
              39.295912
            ],
            [
              -74.654238,
              39.288627
            ],
            [
              -74.668342,
              39.297735
            ],
            [
              -74.673362,
              39.2892
            ],
            [
              -74.676697,
              39.297365
            ],
            [
              -74.699051,
              39.289238
            ],
            [
              -74.719595,
              39.298644
            ],
            [
              -74.7789,
              39.298972
            ],
            [
              -74.784168,
              39.3073
            ],
            [
              -74.824883,
              39.305276
            ],
            [
              -74.860234,
              39.319147
            ],
            [
              -74.864932,
              39.338794
            ],
            [
              -74.851798,
              39.378832
            ],
            [
              -74.855978,
              39.424238
            ],
            [
              -74.985271,
              39.514967
            ],
            [
              -74.736216,
              39.729775
            ],
            [
              -74.667851,
              39.683606
            ],
            [
              -74.654801,
              39.626846
            ],
            [
              -74.639484,
              39.622427
            ],
            [
              -74.634152,
              39.628073
            ],
            [
              -74.628775,
              39.620093
            ],
            [
              -74.621028,
              39.626691
            ],
            [
              -74.576655,
              39.598596
            ],
            [
              -74.553902,
              39.598406
            ],
            [
              -74.539701,
              39.574988
            ],
            [
              -74.525622,
              39.569355
            ],
            [
              -74.514793,
              39.574002
            ],
            [
              -74.493052,
              39.555627
            ],
            [
              -74.462997,
              39.556444
            ],
            [
              -74.45609,
              39.547269
            ],
            [
              -74.446509,
              39.559007
            ],
            [
              -74.445734,
              39.546352
            ],
            [
              -74.4375,
              39.541198
            ],
            [
              -74.43802,
              39.553828
            ],
            [
              -74.417544,
              39.557355
            ],
            [
              -74.380796,
              39.498537
            ],
            [
              -74.326382,
              39.506332
            ],
            [
              -74.312612,
              39.500117
            ],
            [
              -74.296461,
              39.475292
            ],
            [
              -74.232062,
              39.475198
            ],
            [
              -74.287271,
              39.398252
            ],
            [
              -74.374591,
              39.317526
            ],
            [
              -74.46493,
              39.29823
            ],
            [
              -74.565392,
              39.298593
            ],
            [
              -74.586396,
              39.309895
            ]
          ]
        ]
      }
    },
    {
      "type": "Feature",
      "properties": {
        "GEOID": "34021",
        "NAME": "Mercer",
        "NAMELSAD": "Mercer County",
        "STATEFP": "34",
        "COUNTYFP": "021"
      },
      "geometry": {
        "type": "Polygon",
        "coordinates": [
          [
            [
              -74.573397,
              40.3009
            ],
            [
              -74.539918,
              40.28833
            ],
            [
              -74.528142,
              40.2943
            ],
            [
              -74.522873,
              40.285608
            ],
            [
              -74.481991,
              40.273914
            ],
            [
              -74.487407,
              40.253129
            ],
            [
              -74.481095,
              40.243832
            ],
            [
              -74.543302,
              40.21667
            ],
            [
              -74.571241,
              40.185293
            ],
            [
              -74.614576,
              40.182383
            ],
            [
              -74.587835,
              40.138254
            ],
            [
              -74.602112,
              40.13678
            ],
            [
              -74.677425,
              40.166069
            ],
            [
              -74.674436,
              40.173598
            ],
            [
              -74.700421,
              40.183651
            ],
            [
              -74.711072,
              40.180709
            ],
            [
              -74.706269,
              40.161793
            ],
            [
              -74.722048,
              40.150311
            ],
            [
              -74.722325,
              40.160727
            ],
            [
              -74.754305,
              40.185209
            ],
            [
              -74.771437,
              40.215176
            ],
            [
              -74.842308,
              40.250508
            ],
            [
              -74.868208,
              40.295206
            ],
            [
              -74.942909,
              40.341683
            ],
            [
              -74.856262,
              40.346696
            ],
            [
              -74.869678,
              40.377774
            ],
            [
              -74.802016,
              40.384972
            ],
            [
              -74.80847,
              40.416664
            ],
            [
              -74.748147,
              40.424156
            ],
            [
              -74.722061,
              40.375205
            ],
            [
              -74.653928,
              40.391048
            ],
            [
              -74.621462,
              40.383684
            ],
            [
              -74.617505,
              40.377462
            ],
            [
              -74.631036,
              40.340277
            ],
            [
              -74.622462,
              40.3248
            ],
            [
              -74.585587,
              40.313242
            ],
            [
              -74.573397,
              40.3009
            ]
          ]
        ]
      }
    }
  ]
}